<annotation>
  <folder>image_xmls</folder>
  <filename>image-96.png</filename>
  <source>
    <database>coco</database>
  </source>
  <size>
    <width>256</width>
    <height>256</height>
    <depth>3</depth>
  </size>
  <segmented>0</segmented>
  <object>
    <name>wbc</name>
    <pose>Unspecified</pose>
    <truncated>0</truncated>
    <difficult>0</difficult>
    <bndbox>
      <xmin>58.08455468</xmin>
      <ymin>126.1657272</ymin>
      <xmax>144.2029312</xmax>
      <ymax>217.2818489</ymax>
    </bndbox>
  </object>
  <object>
    <name>rbc</name>
    <pose>Unspecified</pose>
    <truncated>0</truncated>
    <difficult>0</difficult>
    <bndbox>
      <xmin>0</xmin>
      <ymin>0</ymin>
      <xmax>34.01240135</xmax>
      <ymax>16.14092446</ymax>
    </bndbox>
  </object>
  <object>
    <name>rbc</name>
    <pose>Unspecified</pose>
    <truncated>0</truncated>
    <difficult>0</difficult>
    <bndbox>
      <xmin>46.45095829</xmin>
      <ymin>0</ymin>
      <xmax>93.84667418</xmax>
      <ymax>12.94926719</ymax>
    </bndbox>
  </object>
  <object>
    <name>rbc</name>
    <pose>Unspecified</pose>
    <truncated>0</truncated>
    <difficult>0</difficult>
    <bndbox>
      <xmin>0</xmin>
      <ymin>16.99549042</ymin>
      <xmax>17.33145434</xmax>
      <ymax>59.91544532</ymax>
    </bndbox>
  </object>
  <object>
    <name>rbc</name>
    <pose>Unspecified</pose>
    <truncated>0</truncated>
    <difficult>0</difficult>
    <bndbox>
      <xmin>0</xmin>
      <ymin>55.98196167</ymin>
      <xmax>19.85907554</xmax>
      <ymax>100.7023675</ymax>
    </bndbox>
  </object>
  <object>
    <name>rbc</name>
    <pose>Unspecified</pose>
    <truncated>0</truncated>
    <difficult>0</difficult>
    <bndbox>
      <xmin>118.6234498</xmin>
      <ymin>0</ymin>
      <xmax>173.1691094</xmax>
      <ymax>14.78466742</ymax>
    </bndbox>
  </object>
  <object>
    <name>rbc</name>
    <pose>Unspecified</pose>
    <truncated>0</truncated>
    <difficult>0</difficult>
    <bndbox>
      <xmin>212.4013529</xmin>
      <ymin>0</ymin>
      <xmax>256</xmax>
      <ymax>10.62232244</ymax>
    </bndbox>
  </object>
  <object>
    <name>rbc</name>
    <pose>Unspecified</pose>
    <truncated>0</truncated>
    <difficult>0</difficult>
    <bndbox>
      <xmin>22.40473506</xmin>
      <ymin>22.93573844</ymin>
      <xmax>73.73055242</xmax>
      <ymax>79.90980834</ymax>
    </bndbox>
  </object>
  <object>
    <name>rbc</name>
    <pose>Unspecified</pose>
    <truncated>0</truncated>
    <difficult>0</difficult>
    <bndbox>
      <xmin>76.28635851</xmin>
      <ymin>1.783540023</ymin>
      <xmax>131.2976325</xmax>
      <ymax>58.42841037</ymax>
    </bndbox>
  </object>
  <object>
    <name>rbc</name>
    <pose>Unspecified</pose>
    <truncated>0</truncated>
    <difficult>0</difficult>
    <bndbox>
      <xmin>156.7508455</xmin>
      <ymin>3.059751973</ymin>
      <xmax>212.5400225</xmax>
      <ymax>56.76550169</ymax>
    </bndbox>
  </object>
  <object>
    <name>rbc</name>
    <pose>Unspecified</pose>
    <truncated>0</truncated>
    <difficult>0</difficult>
    <bndbox>
      <xmin>52.12514092</xmin>
      <ymin>53.45997745</ymin>
      <xmax>102.1612176</xmax>
      <ymax>102.2604284</ymax>
    </bndbox>
  </object>
  <object>
    <name>rbc</name>
    <pose>Unspecified</pose>
    <truncated>0</truncated>
    <difficult>0</difficult>
    <bndbox>
      <xmin>61.24239008</xmin>
      <ymin>77.13641488</ymin>
      <xmax>113.8421646</xmax>
      <ymax>123.6764374</ymax>
    </bndbox>
  </object>
  <object>
    <name>rbc</name>
    <pose>Unspecified</pose>
    <truncated>0</truncated>
    <difficult>0</difficult>
    <bndbox>
      <xmin>164.4723788</xmin>
      <ymin>58.17925592</ymin>
      <xmax>219.4667418</xmax>
      <ymax>110.8703495</ymax>
    </bndbox>
  </object>
  <object>
    <name>rbc</name>
    <pose>Unspecified</pose>
    <truncated>0</truncated>
    <difficult>0</difficult>
    <bndbox>
      <xmin>219.5140924</xmin>
      <ymin>56.23337091</ymin>
      <xmax>254.8105975</xmax>
      <ymax>114.2908681</ymax>
    </bndbox>
  </object>
  <object>
    <name>rbc</name>
    <pose>Unspecified</pose>
    <truncated>0</truncated>
    <difficult>0</difficult>
    <bndbox>
      <xmin>146.7733935</xmin>
      <ymin>67.27057497</ymin>
      <xmax>196.0710259</xmax>
      <ymax>113.3167982</ymax>
    </bndbox>
  </object>
  <object>
    <name>rbc</name>
    <pose>Unspecified</pose>
    <truncated>0</truncated>
    <difficult>0</difficult>
    <bndbox>
      <xmin>0</xmin>
      <ymin>103.1645998</ymin>
      <xmax>41.13754228</xmax>
      <ymax>154.065389</ymax>
    </bndbox>
  </object>
  <object>
    <name>rbc</name>
    <pose>Unspecified</pose>
    <truncated>0</truncated>
    <difficult>0</difficult>
    <bndbox>
      <xmin>32.96505073</xmin>
      <ymin>116.3551297</ymin>
      <xmax>64.51860203</xmax>
      <ymax>174.2142052</ymax>
    </bndbox>
  </object>
  <object>
    <name>rbc</name>
    <pose>Unspecified</pose>
    <truncated>0</truncated>
    <difficult>0</difficult>
    <bndbox>
      <xmin>0</xmin>
      <ymin>140.1420519</ymin>
      <xmax>17.54227734</xmax>
      <ymax>199.8804961</ymax>
    </bndbox>
  </object>
  <object>
    <name>rbc</name>
    <pose>Unspecified</pose>
    <truncated>0</truncated>
    <difficult>0</difficult>
    <bndbox>
      <xmin>0</xmin>
      <ymin>158.6741826</ymin>
      <xmax>44.69334837</xmax>
      <ymax>209.1476888</ymax>
    </bndbox>
  </object>
  <object>
    <name>rbc</name>
    <pose>Unspecified</pose>
    <truncated>0</truncated>
    <difficult>0</difficult>
    <bndbox>
      <xmin>0</xmin>
      <ymin>228.6392334</ymin>
      <xmax>19.6572717</xmax>
      <ymax>252.9763247</ymax>
    </bndbox>
  </object>
  <object>
    <name>rbc</name>
    <pose>Unspecified</pose>
    <truncated>0</truncated>
    <difficult>0</difficult>
    <bndbox>
      <xmin>38.63359639</xmin>
      <ymin>201.6110485</ymin>
      <xmax>92.06877114</xmax>
      <ymax>254.5400225</ymax>
    </bndbox>
  </object>
  <object>
    <name>rbc</name>
    <pose>Unspecified</pose>
    <truncated>0</truncated>
    <difficult>0</difficult>
    <bndbox>
      <xmin>67.70574972</xmin>
      <ymin>224.7812852</ymin>
      <xmax>107.2243517</xmax>
      <ymax>256</ymax>
    </bndbox>
  </object>
  <object>
    <name>rbc</name>
    <pose>Unspecified</pose>
    <truncated>0</truncated>
    <difficult>0</difficult>
    <bndbox>
      <xmin>121.6471251</xmin>
      <ymin>243.3810598</ymin>
      <xmax>185.4396843</xmax>
      <ymax>256</ymax>
    </bndbox>
  </object>
  <object>
    <name>rbc</name>
    <pose>Unspecified</pose>
    <truncated>0</truncated>
    <difficult>0</difficult>
    <bndbox>
      <xmin>209.3370913</xmin>
      <ymin>209.6166855</ymin>
      <xmax>256</xmax>
      <ymax>256</ymax>
    </bndbox>
  </object>
  <object>
    <name>rbc</name>
    <pose>Unspecified</pose>
    <truncated>0</truncated>
    <difficult>0</difficult>
    <bndbox>
      <xmin>190.6674183</xmin>
      <ymin>190.4182638</ymin>
      <xmax>233.6674183</xmax>
      <ymax>248.9391206</ymax>
    </bndbox>
  </object>
  <object>
    <name>rbc</name>
    <pose>Unspecified</pose>
    <truncated>0</truncated>
    <difficult>0</difficult>
    <bndbox>
      <xmin>230.2074408</xmin>
      <ymin>124.6696731</ymin>
      <xmax>256</xmax>
      <ymax>185.3269448</ymax>
    </bndbox>
  </object>
  <object>
    <name>rbc</name>
    <pose>Unspecified</pose>
    <truncated>0</truncated>
    <difficult>0</difficult>
    <bndbox>
      <xmin>182.253664</xmin>
      <ymin>115.8387824</ymin>
      <xmax>228.0326945</xmax>
      <ymax>174.8714769</ymax>
    </bndbox>
  </object>
</annotation>
